first.py
jayshree1-0.2.13.dist-info/LICENCE.txt
jayshree1-0.2.13.dist-info/METADATA
jayshree1-0.2.13.dist-info/WHEEL
jayshree1-0.2.13.dist-info/entry_points.txt
jayshree1-0.2.13.dist-info/top_level.txt
jayshree1-0.2.13.dist-info/RECORD
