Metadata-Version: 2.1
Name: jayshree1
Version: 0.2.13
Summary: A small example package
License: UNKNOWN
Platform: UNKNOWN
License-File: LICENCE.txt
Requires-Dist: Click
Requires-Dist: pyDrive
Requires-Dist: requests
Requires-Dist: python-decouple
Requires-Dist: setuptools
Requires-Dist: pybtex
Requires-Dist: python-dotenv
